{
    "fields": [
        {
            "name": "id",
            "type": "Edm.String",
            "searchable": true,
            "filterable": true,
            "retrievable": true,
            "stored": true,
            "sortable": true,
            "facetable": false,
            "key": true,
            "indexAnalyzer": null,
            "searchAnalyzer": null,
            "analyzer": "keyword",
            "normalizer": null,
            "dimensions": null,
            "vectorSearchProfile": null,
            "vectorEncoding": null,
            "synonymMaps": []
        },
        {
            "name": "content",
            "type": "Edm.String",
            "searchable": true,
            "filterable": false,
            "retrievable": true,
            "stored": true,
            "sortable": false,
            "facetable": false,
            "key": false,
            "indexAnalyzer": null,
            "searchAnalyzer": null,
            "analyzer": null,
            "normalizer": null,
            "dimensions": null,
            "vectorSearchProfile": null,
            "vectorEncoding": null,
            "synonymMaps": []
        },
        {
            "name": "adults",
            "type": "Collection(Edm.ComplexType)",
            "fields": [
                {
                    "name": "isAdultContent",
                    "type": "Edm.Boolean",
                    "searchable": false,
                    "filterable": true,
                    "retrievable": true,
                    "stored": true,
                    "sortable": false,
                    "facetable": true,
                    "key": false,
                    "indexAnalyzer": null,
                    "searchAnalyzer": null,
                    "analyzer": null,
                    "normalizer": null,
                    "dimensions": null,
                    "vectorSearchProfile": null,
                    "vectorEncoding": null,
                    "synonymMaps": []
                },
                {
                    "name": "isGoryContent",
                    "type": "Edm.Boolean",
                    "searchable": false,
                    "filterable": true,
                    "retrievable": true,
                    "stored": true,
                    "sortable": false,
                    "facetable": true,
                    "key": false,
                    "indexAnalyzer": null,
                    "searchAnalyzer": null,
                    "analyzer": null,
                    "normalizer": null,
                    "dimensions": null,
                    "vectorSearchProfile": null,
                    "vectorEncoding": null,
                    "synonymMaps": []
                },
                {
                    "name": "isRacyContent",
                    "type": "Edm.Boolean",
                    "searchable": false,
                    "filterable": true,
                    "retrievable": true,
                    "stored": true,
                    "sortable": false,
                    "facetable": true,
                    "key": false,
                    "indexAnalyzer": null,
                    "searchAnalyzer": null,
                    "analyzer": null,
                    "normalizer": null,
                    "dimensions": null,
                    "vectorSearchProfile": null,
                    "vectorEncoding": null,
                    "synonymMaps": []
                },
                {
                    "name": "adultScore",
                    "type": "Edm.Double",
                    "searchable": false,
                    "filterable": false,
                    "retrievable": true,
                    "stored": true,
                    "sortable": false,
                    "facetable": false,
                    "key": false,
                    "indexAnalyzer": null,
                    "searchAnalyzer": null,
                    "analyzer": null,
                    "normalizer": null,
                    "dimensions": null,
                    "vectorSearchProfile": null,
                    "vectorEncoding": null,
                    "synonymMaps": []
                },
                {
                    "name": "goreScore",
                    "type": "Edm.Double",
                    "searchable": false,
                    "filterable": false,
                    "retrievable": true,
                    "stored": true,
                    "sortable": false,
                    "facetable": false,
                    "key": false,
                    "indexAnalyzer": null,
                    "searchAnalyzer": null,
                    "analyzer": null,
                    "normalizer": null,
                    "dimensions": null,
                    "vectorSearchProfile": null,
                    "vectorEncoding": null,
                    "synonymMaps": []
                },
                {
                    "name": "racyScore",
                    "type": "Edm.Double",
                    "searchable": false,
                    "filterable": false,
                    "retrievable": true,
                    "stored": true,
                    "sortable": false,
                    "facetable": false,
                    "key": false,
                    "indexAnalyzer": null,
                    "searchAnalyzer": null,
                    "analyzer": null,
                    "normalizer": null,
                    "dimensions": null,
                    "vectorSearchProfile": null,
                    "vectorEncoding": null,
                    "synonymMaps": []
                }
            ]
        },
        {
            "name": "brands",
            "type": "Collection(Edm.ComplexType)",
            "fields": [
                {
                    "name": "name",
                    "type": "Edm.String",
                    "searchable": true,
                    "filterable": false,
                    "retrievable": true,
                    "stored": true,
                    "sortable": false,
                    "facetable": false,
                    "key": false,
                    "indexAnalyzer": null,
                    "searchAnalyzer": null,
                    "analyzer": null,
                    "normalizer": null,
                    "dimensions": null,
                    "vectorSearchProfile": null,
                    "vectorEncoding": null,
                    "synonymMaps": []
                },
                {
                    "name": "confidence",
                    "type": "Edm.Double",
                    "searchable": false,
                    "filterable": false,
                    "retrievable": true,
                    "stored": true,
                    "sortable": false,
                    "facetable": false,
                    "key": false,
                    "indexAnalyzer": null,
                    "searchAnalyzer": null,
                    "analyzer": null,
                    "normalizer": null,
                    "dimensions": null,
                    "vectorSearchProfile": null,
                    "vectorEncoding": null,
                    "synonymMaps": []
                },
                {
                    "name": "rectangle",
                    "type": "Edm.ComplexType",
                    "fields": [
                        {
                            "name": "x",
                            "type": "Edm.Int32",
                            "searchable": false,
                            "filterable": false,
                            "retrievable": true,
                            "stored": true,
                            "sortable": false,
                            "facetable": false,
                            "key": false,
                            "indexAnalyzer": null,
                            "searchAnalyzer": null,
                            "analyzer": null,
                            "normalizer": null,
                            "dimensions": null,
                            "vectorSearchProfile": null,
                            "vectorEncoding": null,
                            "synonymMaps": []
                        },
                        {
                            "name": "y",
                            "type": "Edm.Int32",
                            "searchable": false,
                            "filterable": false,
                            "retrievable": true,
                            "stored": true,
                            "sortable": false,
                            "facetable": false,
                            "key": false,
                            "indexAnalyzer": null,
                            "searchAnalyzer": null,
                            "analyzer": null,
                            "normalizer": null,
                            "dimensions": null,
                            "vectorSearchProfile": null,
                            "vectorEncoding": null,
                            "synonymMaps": []
                        },
                        {
                            "name": "w",
                            "type": "Edm.Int32",
                            "searchable": false,
                            "filterable": false,
                            "retrievable": true,
                            "stored": true,
                            "sortable": false,
                            "facetable": false,
                            "key": false,
                            "indexAnalyzer": null,
                            "searchAnalyzer": null,
                            "analyzer": null,
                            "normalizer": null,
                            "dimensions": null,
                            "vectorSearchProfile": null,
                            "vectorEncoding": null,
                            "synonymMaps": []
                        },
                        {
                            "name": "h",
                            "type": "Edm.Int32",
                            "searchable": false,
                            "filterable": false,
                            "retrievable": true,
                            "stored": true,
                            "sortable": false,
                            "facetable": false,
                            "key": false,
                            "indexAnalyzer": null,
                            "searchAnalyzer": null,
                            "analyzer": null,
                            "normalizer": null,
                            "dimensions": null,
                            "vectorSearchProfile": null,
                            "vectorEncoding": null,
                            "synonymMaps": []
                        }
                    ]
                }
            ]
        },
        {
            "name": "categories",
            "type": "Collection(Edm.ComplexType)",
            "fields": [
                {
                    "name": "name",
                    "type": "Edm.String",
                    "searchable": true,
                    "filterable": false,
                    "retrievable": true,
                    "stored": true,
                    "sortable": false,
                    "facetable": false,
                    "key": false,
                    "indexAnalyzer": null,
                    "searchAnalyzer": null,
                    "analyzer": null,
                    "normalizer": null,
                    "dimensions": null,
                    "vectorSearchProfile": null,
                    "vectorEncoding": null,
                    "synonymMaps": []
                },
                {
                    "name": "score",
                    "type": "Edm.Double",
                    "searchable": false,
                    "filterable": false,
                    "retrievable": true,
                    "stored": true,
                    "sortable": false,
                    "facetable": false,
                    "key": false,
                    "indexAnalyzer": null,
                    "searchAnalyzer": null,
                    "analyzer": null,
                    "normalizer": null,
                    "dimensions": null,
                    "vectorSearchProfile": null,
                    "vectorEncoding": null,
                    "synonymMaps": []
                },
                {
                    "name": "detail",
                    "type": "Edm.ComplexType",
                    "fields": [
                        {
                            "name": "celebrities",
                            "type": "Collection(Edm.ComplexType)",
                            "fields": [
                                {
                                    "name": "name",
                                    "type": "Edm.String",
                                    "searchable": true,
                                    "filterable": false,
                                    "retrievable": true,
                                    "stored": true,
                                    "sortable": false,
                                    "facetable": false,
                                    "key": false,
                                    "indexAnalyzer": null,
                                    "searchAnalyzer": null,
                                    "analyzer": null,
                                    "normalizer": null,
                                    "dimensions": null,
                                    "vectorSearchProfile": null,
                                    "vectorEncoding": null,
                                    "synonymMaps": []
                                },
                                {
                                    "name": "faceBoundingBox",
                                    "type": "Collection(Edm.ComplexType)",
                                    "fields": [
                                        {
                                            "name": "x",
                                            "type": "Edm.Int32",
                                            "searchable": false,
                                            "filterable": false,
                                            "retrievable": true,
                                            "stored": true,
                                            "sortable": false,
                                            "facetable": false,
                                            "key": false,
                                            "indexAnalyzer": null,
                                            "searchAnalyzer": null,
                                            "analyzer": null,
                                            "normalizer": null,
                                            "dimensions": null,
                                            "vectorSearchProfile": null,
                                            "vectorEncoding": null,
                                            "synonymMaps": []
                                        },
                                        {
                                            "name": "y",
                                            "type": "Edm.Int32",
                                            "searchable": false,
                                            "filterable": false,
                                            "retrievable": true,
                                            "stored": true,
                                            "sortable": false,
                                            "facetable": false,
                                            "key": false,
                                            "indexAnalyzer": null,
                                            "searchAnalyzer": null,
                                            "analyzer": null,
                                            "normalizer": null,
                                            "dimensions": null,
                                            "vectorSearchProfile": null,
                                            "vectorEncoding": null,
                                            "synonymMaps": []
                                        }
                                    ]
                                },
                                {
                                    "name": "confidence",
                                    "type": "Edm.Double",
                                    "searchable": false,
                                    "filterable": false,
                                    "retrievable": true,
                                    "stored": true,
                                    "sortable": false,
                                    "facetable": false,
                                    "key": false,
                                    "indexAnalyzer": null,
                                    "searchAnalyzer": null,
                                    "analyzer": null,
                                    "normalizer": null,
                                    "dimensions": null,
                                    "vectorSearchProfile": null,
                                    "vectorEncoding": null,
                                    "synonymMaps": []
                                }
                            ]
                        },
                        {
                            "name": "landmarks",
                            "type": "Collection(Edm.ComplexType)",
                            "fields": [
                                {
                                    "name": "name",
                                    "type": "Edm.String",
                                    "searchable": true,
                                    "filterable": false,
                                    "retrievable": true,
                                    "stored": true,
                                    "sortable": false,
                                    "facetable": false,
                                    "key": false,
                                    "indexAnalyzer": null,
                                    "searchAnalyzer": null,
                                    "analyzer": null,
                                    "normalizer": null,
                                    "dimensions": null,
                                    "vectorSearchProfile": null,
                                    "vectorEncoding": null,
                                    "synonymMaps": []
                                },
                                {
                                    "name": "confidence",
                                    "type": "Edm.Double",
                                    "searchable": false,
                                    "filterable": false,
                                    "retrievable": true,
                                    "stored": true,
                                    "sortable": false,
                                    "facetable": false,
                                    "key": false,
                                    "indexAnalyzer": null,
                                    "searchAnalyzer": null,
                                    "analyzer": null,
                                    "normalizer": null,
                                    "dimensions": null,
                                    "vectorSearchProfile": null,
                                    "vectorEncoding": null,
                                    "synonymMaps": []
                                }
                            ]
                        }
                    ]
                }
            ]
        },
        {
            "name": "description",
            "type": "Collection(Edm.ComplexType)",
            "fields": [
                {
                    "name": "tags",
                    "type": "Collection(Edm.String)",
                    "searchable": true,
                    "filterable": false,
                    "retrievable": true,
                    "stored": true,
                    "sortable": false,
                    "facetable": false,
                    "key": false,
                    "indexAnalyzer": null,
                    "searchAnalyzer": null,
                    "analyzer": null,
                    "normalizer": null,
                    "dimensions": null,
                    "vectorSearchProfile": null,
                    "vectorEncoding": null,
                    "synonymMaps": []
                },
                {
                    "name": "captions",
                    "type": "Collection(Edm.ComplexType)",
                    "fields": [
                        {
                            "name": "text",
                            "type": "Edm.String",
                            "searchable": true,
                            "filterable": false,
                            "retrievable": true,
                            "stored": true,
                            "sortable": false,
                            "facetable": false,
                            "key": false,
                            "indexAnalyzer": null,
                            "searchAnalyzer": null,
                            "analyzer": null,
                            "normalizer": null,
                            "dimensions": null,
                            "vectorSearchProfile": null,
                            "vectorEncoding": null,
                            "synonymMaps": []
                        },
                        {
                            "name": "confidence",
                            "type": "Edm.Double",
                            "searchable": false,
                            "filterable": false,
                            "retrievable": true,
                            "stored": true,
                            "sortable": false,
                            "facetable": false,
                            "key": false,
                            "indexAnalyzer": null,
                            "searchAnalyzer": null,
                            "analyzer": null,
                            "normalizer": null,
                            "dimensions": null,
                            "vectorSearchProfile": null,
                            "vectorEncoding": null,
                            "synonymMaps": []
                        }
                    ]
                }
            ]
        },
        {
            "name": "faces",
            "type": "Collection(Edm.ComplexType)",
            "fields": [
                {
                    "name": "age",
                    "type": "Edm.Int32",
                    "searchable": false,
                    "filterable": false,
                    "retrievable": true,
                    "stored": true,
                    "sortable": false,
                    "facetable": false,
                    "key": false,
                    "indexAnalyzer": null,
                    "searchAnalyzer": null,
                    "analyzer": null,
                    "normalizer": null,
                    "dimensions": null,
                    "vectorSearchProfile": null,
                    "vectorEncoding": null,
                    "synonymMaps": []
                },
                {
                    "name": "gender",
                    "type": "Edm.String",
                    "searchable": false,
                    "filterable": false,
                    "retrievable": true,
                    "stored": true,
                    "sortable": false,
                    "facetable": false,
                    "key": false,
                    "indexAnalyzer": null,
                    "searchAnalyzer": null,
                    "analyzer": null,
                    "normalizer": null,
                    "dimensions": null,
                    "vectorSearchProfile": null,
                    "vectorEncoding": null,
                    "synonymMaps": []
                },
                {
                    "name": "faceBoundingBox",
                    "type": "Collection(Edm.ComplexType)",
                    "fields": [
                        {
                            "name": "top",
                            "type": "Edm.Int32",
                            "searchable": false,
                            "filterable": false,
                            "retrievable": true,
                            "stored": true,
                            "sortable": false,
                            "facetable": false,
                            "key": false,
                            "indexAnalyzer": null,
                            "searchAnalyzer": null,
                            "analyzer": null,
                            "normalizer": null,
                            "dimensions": null,
                            "vectorSearchProfile": null,
                            "vectorEncoding": null,
                            "synonymMaps": []
                        },
                        {
                            "name": "left",
                            "type": "Edm.Int32",
                            "searchable": false,
                            "filterable": false,
                            "retrievable": true,
                            "stored": true,
                            "sortable": false,
                            "facetable": false,
                            "key": false,
                            "indexAnalyzer": null,
                            "searchAnalyzer": null,
                            "analyzer": null,
                            "normalizer": null,
                            "dimensions": null,
                            "vectorSearchProfile": null,
                            "vectorEncoding": null,
                            "synonymMaps": []
                        },
                        {
                            "name": "width",
                            "type": "Edm.Int32",
                            "searchable": false,
                            "filterable": false,
                            "retrievable": true,
                            "stored": true,
                            "sortable": false,
                            "facetable": false,
                            "key": false,
                            "indexAnalyzer": null,
                            "searchAnalyzer": null,
                            "analyzer": null,
                            "normalizer": null,
                            "dimensions": null,
                            "vectorSearchProfile": null,
                            "vectorEncoding": null,
                            "synonymMaps": []
                        },
                        {
                            "name": "height",
                            "type": "Edm.Int32",
                            "searchable": false,
                            "filterable": false,
                            "retrievable": true,
                            "stored": true,
                            "sortable": false,
                            "facetable": false,
                            "key": false,
                            "indexAnalyzer": null,
                            "searchAnalyzer": null,
                            "analyzer": null,
                            "normalizer": null,
                            "dimensions": null,
                            "vectorSearchProfile": null,
                            "vectorEncoding": null,
                            "synonymMaps": []
                        }
                    ]
                }
            ]
        },
        {
            "name": "objects",
            "type": "Collection(Edm.ComplexType)",
            "fields": [
                {
                    "name": "object",
                    "type": "Edm.String",
                    "searchable": true,
                    "filterable": false,
                    "retrievable": true,
                    "stored": true,
                    "sortable": false,
                    "facetable": false,
                    "key": false,
                    "indexAnalyzer": null,
                    "searchAnalyzer": null,
                    "analyzer": null,
                    "normalizer": null,
                    "dimensions": null,
                    "vectorSearchProfile": null,
                    "vectorEncoding": null,
                    "synonymMaps": []
                },
                {
                    "name": "confidence",
                    "type": "Edm.Double",
                    "searchable": false,
                    "filterable": false,
                    "retrievable": true,
                    "stored": true,
                    "sortable": false,
                    "facetable": false,
                    "key": false,
                    "indexAnalyzer": null,
                    "searchAnalyzer": null,
                    "analyzer": null,
                    "normalizer": null,
                    "dimensions": null,
                    "vectorSearchProfile": null,
                    "vectorEncoding": null,
                    "synonymMaps": []
                },
                {
                    "name": "rectangle",
                    "type": "Edm.ComplexType",
                    "fields": [
                        {
                            "name": "x",
                            "type": "Edm.Int32",
                            "searchable": false,
                            "filterable": false,
                            "retrievable": true,
                            "stored": true,
                            "sortable": false,
                            "facetable": false,
                            "key": false,
                            "indexAnalyzer": null,
                            "searchAnalyzer": null,
                            "analyzer": null,
                            "normalizer": null,
                            "dimensions": null,
                            "vectorSearchProfile": null,
                            "vectorEncoding": null,
                            "synonymMaps": []
                        },
                        {
                            "name": "y",
                            "type": "Edm.Int32",
                            "searchable": false,
                            "filterable": false,
                            "retrievable": true,
                            "stored": true,
                            "sortable": false,
                            "facetable": false,
                            "key": false,
                            "indexAnalyzer": null,
                            "searchAnalyzer": null,
                            "analyzer": null,
                            "normalizer": null,
                            "dimensions": null,
                            "vectorSearchProfile": null,
                            "vectorEncoding": null,
                            "synonymMaps": []
                        },
                        {
                            "name": "w",
                            "type": "Edm.Int32",
                            "searchable": false,
                            "filterable": false,
                            "retrievable": true,
                            "stored": true,
                            "sortable": false,
                            "facetable": false,
                            "key": false,
                            "indexAnalyzer": null,
                            "searchAnalyzer": null,
                            "analyzer": null,
                            "normalizer": null,
                            "dimensions": null,
                            "vectorSearchProfile": null,
                            "vectorEncoding": null,
                            "synonymMaps": []
                        },
                        {
                            "name": "h",
                            "type": "Edm.Int32",
                            "searchable": false,
                            "filterable": false,
                            "retrievable": true,
                            "stored": true,
                            "sortable": false,
                            "facetable": false,
                            "key": false,
                            "indexAnalyzer": null,
                            "searchAnalyzer": null,
                            "analyzer": null,
                            "normalizer": null,
                            "dimensions": null,
                            "vectorSearchProfile": null,
                            "vectorEncoding": null,
                            "synonymMaps": []
                        }
                    ]
                },
                {
                    "name": "parent",
                    "type": "Edm.ComplexType",
                    "fields": [
                        {
                            "name": "object",
                            "type": "Edm.String",
                            "searchable": true,
                            "filterable": false,
                            "retrievable": true,
                            "stored": true,
                            "sortable": false,
                            "facetable": false,
                            "key": false,
                            "indexAnalyzer": null,
                            "searchAnalyzer": null,
                            "analyzer": null,
                            "normalizer": null,
                            "dimensions": null,
                            "vectorSearchProfile": null,
                            "vectorEncoding": null,
                            "synonymMaps": []
                        },
                        {
                            "name": "confidence",
                            "type": "Edm.Double",
                            "searchable": false,
                            "filterable": false,
                            "retrievable": true,
                            "stored": true,
                            "sortable": false,
                            "facetable": false,
                            "key": false,
                            "indexAnalyzer": null,
                            "searchAnalyzer": null,
                            "analyzer": null,
                            "normalizer": null,
                            "dimensions": null,
                            "vectorSearchProfile": null,
                            "vectorEncoding": null,
                            "synonymMaps": []
                        }
                    ]
                }
            ]
        },
        {
            "name": "tags",
            "type": "Collection(Edm.ComplexType)",
            "fields": [
                {
                    "name": "name",
                    "type": "Edm.String",
                    "searchable": true,
                    "filterable": false,
                    "retrievable": true,
                    "stored": true,
                    "sortable": false,
                    "facetable": false,
                    "key": false,
                    "indexAnalyzer": null,
                    "searchAnalyzer": null,
                    "analyzer": null,
                    "normalizer": null,
                    "dimensions": null,
                    "vectorSearchProfile": null,
                    "vectorEncoding": null,
                    "synonymMaps": []
                },
                {
                    "name": "hint",
                    "type": "Edm.String",
                    "searchable": true,
                    "filterable": false,
                    "retrievable": true,
                    "stored": true,
                    "sortable": false,
                    "facetable": false,
                    "key": false,
                    "indexAnalyzer": null,
                    "searchAnalyzer": null,
                    "analyzer": null,
                    "normalizer": null,
                    "dimensions": null,
                    "vectorSearchProfile": null,
                    "vectorEncoding": null,
                    "synonymMaps": []
                },
                {
                    "name": "confidence",
                    "type": "Edm.Double",
                    "searchable": false,
                    "filterable": false,
                    "retrievable": true,
                    "stored": true,
                    "sortable": false,
                    "facetable": false,
                    "key": false,
                    "indexAnalyzer": null,
                    "searchAnalyzer": null,
                    "analyzer": null,
                    "normalizer": null,
                    "dimensions": null,
                    "vectorSearchProfile": null,
                    "vectorEncoding": null,
                    "synonymMaps": []
                }
            ]
        },
        {
            "name": "metadata_storage_name",
            "type": "Edm.String",
            "searchable": true,
            "filterable": false,
            "retrievable": true,
            "stored": true,
            "sortable": true,
            "facetable": true,
            "key": false,
            "indexAnalyzer": null,
            "searchAnalyzer": null,
            "analyzer": "keyword",
            "normalizer": null,
            "dimensions": null,
            "vectorSearchProfile": null,
            "vectorEncoding": null,
            "synonymMaps": []
        },
        {
            "name": "metadata_storage_path",
            "type": "Edm.String",
            "searchable": true,
            "filterable": false,
            "retrievable": true,
            "stored": true,
            "sortable": true,
            "facetable": true,
            "key": false,
            "indexAnalyzer": null,
            "searchAnalyzer": null,
            "analyzer": null,
            "normalizer": null,
            "dimensions": null,
            "vectorSearchProfile": null,
            "vectorEncoding": null,
            "synonymMaps": []
        },
        {
            "name": "metadata_storage_size",
            "type": "Edm.Int64",
            "searchable": false,
            "filterable": true,
            "retrievable": true,
            "stored": true,
            "sortable": true,
            "facetable": true,
            "key": false,
            "indexAnalyzer": null,
            "searchAnalyzer": null,
            "analyzer": null,
            "normalizer": null,
            "dimensions": null,
            "vectorSearchProfile": null,
            "vectorEncoding": null,
            "synonymMaps": []
        },
        {
            "name": "metadata_storage_content_type",
            "type": "Edm.String",
            "searchable": false,
            "filterable": true,
            "retrievable": true,
            "stored": true,
            "sortable": true,
            "facetable": true,
            "key": false,
            "indexAnalyzer": null,
            "searchAnalyzer": null,
            "analyzer": null,
            "normalizer": null,
            "dimensions": null,
            "vectorSearchProfile": null,
            "vectorEncoding": null,
            "synonymMaps": []
        },
        {
            "name": "metadata_language",
            "type": "Edm.String",
            "searchable": false,
            "filterable": true,
            "retrievable": true,
            "stored": true,
            "sortable": true,
            "facetable": true,
            "key": false,
            "indexAnalyzer": null,
            "searchAnalyzer": null,
            "analyzer": null,
            "normalizer": null,
            "dimensions": null,
            "vectorSearchProfile": null,
            "vectorEncoding": null,
            "synonymMaps": []
        },
        {
            "name": "metadata_author",
            "type": "Edm.String",
            "searchable": true,
            "filterable": true,
            "retrievable": true,
            "stored": true,
            "sortable": true,
            "facetable": true,
            "key": false,
            "indexAnalyzer": null,
            "searchAnalyzer": null,
            "analyzer": null,
            "normalizer": null,
            "dimensions": null,
            "vectorSearchProfile": null,
            "vectorEncoding": null,
            "synonymMaps": []
        },
        {
            "name": "metadata_creation_date",
            "type": "Edm.String",
            "searchable": false,
            "filterable": true,
            "retrievable": true,
            "stored": true,
            "sortable": true,
            "facetable": true,
            "key": false,
            "indexAnalyzer": null,
            "searchAnalyzer": null,
            "analyzer": null,
            "normalizer": null,
            "dimensions": null,
            "vectorSearchProfile": null,
            "vectorEncoding": null,
            "synonymMaps": []
        }
    ],
    "defaultScoringProfile": null,
    "scoringProfiles": [],
    "corsOptions": null,
    "suggesters": [],
    "analyzers": [],
    "normalizers": [],
    "tokenizers": [],
    "tokenFilters": [],
    "charFilters": [],
    "encryptionKey": null,
    "similarity": {
        "@odata.type": "#Microsoft.Azure.Search.BM25Similarity",
        "k1": null,
        "b": null
    },
    "semantic": null,
    "vectorSearch": null
}